sphinx_datatables/__init__.py
sphinx_datatables/activate_datatables.js.in
sphinx_datatables/sphinx_datatables.py
sphinx_datatables-0.5.0.dist-info/licenses/LICENSE
sphinx_datatables-0.5.0.dist-info/METADATA
sphinx_datatables-0.5.0.dist-info/WHEEL
sphinx_datatables-0.5.0.dist-info/top_level.txt
sphinx_datatables-0.5.0.dist-info/RECORD
