Metadata-Version: 2.4
Name: sphinx-datatables
Version: 0.5.0
Summary: Searchable and sortable tables in Sphinx documentation
Author-email: Varun Sharma <29899983+sharm294@users.noreply.github.com>
License: MIT License
Project-URL: Home, https://github.com/sharm294/sphinx-datatables
Project-URL: Documentation, https://sharm294.github.io/sphinx-datatables/
Keywords: sphinx,table,datatables
Classifier: Development Status :: 4 - Beta
Classifier: Framework :: Sphinx :: Extension
Classifier: Intended Audience :: Developers
Classifier: License :: OSI Approved :: MIT License
Classifier: Programming Language :: Python :: 3
Requires-Python: >=3.10
License-File: LICENSE
Requires-Dist: sphinx>4
Requires-Dist: sphinxcontrib_jquery>=4.1
Requires-Dist: packaging
Provides-Extra: docs
Requires-Dist: sphinx-toolbox; extra == "docs"
Requires-Dist: sphinx-copybutton; extra == "docs"
Provides-Extra: dev
Requires-Dist: pytest; extra == "dev"
Dynamic: license-file
